inworld_python/__init__.py
inworld_python/inworld_chat.py
inworld_python-0.0.10.dist-info/LICENSE
inworld_python-0.0.10.dist-info/METADATA
inworld_python-0.0.10.dist-info/WHEEL
inworld_python-0.0.10.dist-info/top_level.txt
inworld_python-0.0.10.dist-info/RECORD
