Metadata-Version: 2.1
Name: inworld-python
Version: 0.0.10
Summary: Inworld Wrapper for Python
Author: Edgelord (Lucky Robinson)
Author-email: <luckstarsfilm@gmail.com>
Keywords: python,Inworld,NPC,Game Characters
Classifier: Development Status :: 1 - Planning
Classifier: Intended Audience :: Developers
Classifier: Programming Language :: Python :: 3
Classifier: Operating System :: Unix
Classifier: Operating System :: MacOS :: MacOS X
Classifier: Operating System :: Microsoft :: Windows
License-File: LICENSE
Requires-Dist: nodejs-bin
